Metadata-Version: 2.1
Name: sma2mqtt
Version: 0.0.13
Summary: Command line tool that listens to the multicast Speedwire of a SMA Energy Meter/Home Manger 2.0 and writes the values to a MQTT server.
Home-page: https://github.com/vindolin/sma2mqtt
Author: Thomas Schüßler
License: MIT
Keywords: sma,mqtt
Classifier: Development Status :: 4 - Beta
Classifier: License :: OSI Approved :: MIT License
Classifier: Programming Language :: Python :: 3.7
License-File: LICENSE
